proxy_grabber.py
proxy_grabber-1.1.1.dist-info/LICENSE
proxy_grabber-1.1.1.dist-info/METADATA
proxy_grabber-1.1.1.dist-info/WHEEL
proxy_grabber-1.1.1.dist-info/top_level.txt
proxy_grabber-1.1.1.dist-info/RECORD
