Metadata-Version: 2.1
Name: proxy-grabber
Version: 1.1.1
Summary: Simple http proxy grabber and checker
Home-page: https://github.com/Ferluci/Proxy-Grabber
Author: Anischenko Konstantin
Author-email: anishenko00@gmail.com
License: UNKNOWN
Keywords: proxy grabber http proxy-grabber scrapper web
Platform: UNKNOWN
Classifier: Development Status :: 5 - Production/Stable
Classifier: Intended Audience :: Developers
Classifier: Topic :: Software Development
Classifier: Programming Language :: Python :: 3.5
Classifier: Programming Language :: Python :: 3.6
Requires-Dist: requests (>=2.20.0)
Requires-Dist: beautifulsoup4 (>=4.6.0)
